zool/__init__.py
zool/__main__.py
zool/filter_plugins.py
zool/github.py
zool/ui.py
zool/utils.py
zool/zool.py
zool/zuul.py
zool-1.3.0.dist-info/LICENSE
zool-1.3.0.dist-info/METADATA
zool-1.3.0.dist-info/WHEEL
zool-1.3.0.dist-info/entry_points.txt
zool-1.3.0.dist-info/top_level.txt
zool-1.3.0.dist-info/RECORD
