Metadata-Version: 2.1
Name: zool
Version: 1.3.0
Summary: A cli for reviewing PRs and zuul's progress
Home-page: UNKNOWN
Author: cidrblock
License: UNKNOWN
Platform: UNKNOWN
Requires-Dist: jinja2
Requires-Dist: pyyaml
Requires-Dist: requests
Requires-Dist: pygments
Requires-Dist: lxml
